llama_index/packs/code_hierarchy/__init__.py
llama_index/packs/code_hierarchy/base.py
llama_index/packs/code_hierarchy/code_hierarchy.py
llama_index/packs/code_hierarchy/query_engine.py
llama_index/packs/code_hierarchy/pytree-sitter-queries/tree-sitter-c-tags.scm
llama_index/packs/code_hierarchy/pytree-sitter-queries/tree-sitter-c_sharp-tags.scm
llama_index/packs/code_hierarchy/pytree-sitter-queries/tree-sitter-cpp-tags.scm
llama_index/packs/code_hierarchy/pytree-sitter-queries/tree-sitter-elisp-tags.scm
llama_index/packs/code_hierarchy/pytree-sitter-queries/tree-sitter-elixir-tags.scm
llama_index/packs/code_hierarchy/pytree-sitter-queries/tree-sitter-elm-tags.scm
llama_index/packs/code_hierarchy/pytree-sitter-queries/tree-sitter-go-tags.scm
llama_index/packs/code_hierarchy/pytree-sitter-queries/tree-sitter-java-tags.scm
llama_index/packs/code_hierarchy/pytree-sitter-queries/tree-sitter-javascript-tags.scm
llama_index/packs/code_hierarchy/pytree-sitter-queries/tree-sitter-ocaml-tags.scm
llama_index/packs/code_hierarchy/pytree-sitter-queries/tree-sitter-php-tags.scm
llama_index/packs/code_hierarchy/pytree-sitter-queries/tree-sitter-python-tags.scm
llama_index/packs/code_hierarchy/pytree-sitter-queries/tree-sitter-ql-tags.scm
llama_index/packs/code_hierarchy/pytree-sitter-queries/tree-sitter-ruby-tags.scm
llama_index/packs/code_hierarchy/pytree-sitter-queries/tree-sitter-rust-tags.scm
llama_index/packs/code_hierarchy/pytree-sitter-queries/tree-sitter-typescript-tags.scm
llama_index_packs_code_hierarchy-0.6.1.dist-info/METADATA
llama_index_packs_code_hierarchy-0.6.1.dist-info/WHEEL
llama_index_packs_code_hierarchy-0.6.1.dist-info/licenses/LICENSE
llama_index_packs_code_hierarchy-0.6.1.dist-info/RECORD
