Metadata-Version: 2.4
Name: llama-index-packs-code-hierarchy
Version: 0.6.1
Summary: A node parser which can create a hierarchy of all code scopes in a directory.
Author-email: Ryan Peach <rgpeach10@gmail.com>
Maintainer: ryanpeach
License-Expression: MIT
License-File: LICENSE
Keywords: c,code,cpp,hierarchy,html,javascript,python,repo,typescript
Requires-Python: <3.13,>=3.9
Requires-Dist: llama-index-core<0.15,>=0.13.0
Requires-Dist: llama-index-readers-file<0.6,>=0.5.0
Requires-Dist: tree-sitter
Requires-Dist: tree-sitter-language-pack
